odoo/addons/purchase_invoice_plan_retention/README.rst
odoo/addons/purchase_invoice_plan_retention/__init__.py
odoo/addons/purchase_invoice_plan_retention/__manifest__.py
odoo/addons/purchase_invoice_plan_retention/i18n/es.po
odoo/addons/purchase_invoice_plan_retention/i18n/it.po
odoo/addons/purchase_invoice_plan_retention/i18n/purchase_invoice_plan_retention.pot
odoo/addons/purchase_invoice_plan_retention/models/__init__.py
odoo/addons/purchase_invoice_plan_retention/models/purchase.py
odoo/addons/purchase_invoice_plan_retention/readme/CONTRIBUTORS.rst
odoo/addons/purchase_invoice_plan_retention/readme/DESCRIPTION.rst
odoo/addons/purchase_invoice_plan_retention/readme/USAGE.rst
odoo/addons/purchase_invoice_plan_retention/static/description/icon.png
odoo/addons/purchase_invoice_plan_retention/static/description/index.html
odoo/addons/purchase_invoice_plan_retention/tests/__init__.py
odoo/addons/purchase_invoice_plan_retention/tests/test_purchase_invoice_plan_retention.py
odoo/addons/purchase_invoice_plan_retention/views/purchase_view.xml
odoo14_addon_purchase_invoice_plan_retention-14.0.1.0.1.dev8.dist-info/METADATA
odoo14_addon_purchase_invoice_plan_retention-14.0.1.0.1.dev8.dist-info/WHEEL
odoo14_addon_purchase_invoice_plan_retention-14.0.1.0.1.dev8.dist-info/top_level.txt
odoo14_addon_purchase_invoice_plan_retention-14.0.1.0.1.dev8.dist-info/RECORD
