Metadata-Version: 2.1
Name: odoo14-addon-purchase_invoice_plan_retention
Version: 14.0.1.0.1.dev8
Summary: Add to purchase invoice plan, the retention on each invoice
Home-page: https://github.com/OCA/purchase-workflow
Author: Ecosoft,Odoo Community Association (OCA)
Author-email: support@odoo-community.org
License: AGPL-3
Classifier: Programming Language :: Python
Classifier: Framework :: Odoo
Classifier: Framework :: Odoo :: 14.0
Classifier: License :: OSI Approved :: GNU Affero General Public License v3
Classifier: Development Status :: 3 - Alpha
Requires-Python: >=3.6
Requires-Dist: odoo14-addon-account-invoice-payment-retention
Requires-Dist: odoo14-addon-purchase-invoice-plan
Requires-Dist: odoo<14.1dev,>=14.0a
